hexviewer/__init__.py
hexviewer/hexviewer
hexviewer/hexviewer.py
hexviewer/test.py
hexviewer-0.1.4.data/scripts/hexviewer
hexviewer-0.1.4.data/scripts/hexviewer.py
hexviewer-0.1.4.dist-info/METADATA
hexviewer-0.1.4.dist-info/WHEEL
hexviewer-0.1.4.dist-info/top_level.txt
hexviewer-0.1.4.dist-info/RECORD
