Metadata-Version: 2.1
Name: hexviewer
Version: 0.1.4
Summary: hexviewer
Home-page: https://github.com/dankernel/hexviewer
Author: dankernel
Author-email: dkdkernel@gmail.com
License: UNKNOWN
Platform: UNKNOWN
Classifier: Programming Language :: Python :: 3
Classifier: License :: OSI Approved :: MIT License
Classifier: Operating System :: OS Independent
Requires-Python: >=3.6
Requires-Dist: python-telegram-bot
